[
    {
        "name": "DOEL Freedom A9 AMD A9-9425 14.1 HD Laptop",
        "categoryName": "all-laptop",
        "brand": "DOEL",
        "price": "29,999৳",
        "img": "https://www.startech.com.bd/image/cache/catalog/laptop/doel/freedom-a9/a9-01-228x228.webp",
        "newPrice": "27,999৳",
        "processor": "Processor: AMD A9-9425 (1MB Cache, 3.10GHz up to 3.70GHz)",
        "color": "Black",
        "Ram": "RAM: 4GB",
        "CPU Cache": "1MB",
        "Display Size": "Display: 14.1 inch",
        "Battery Capacity": "7.6V, 41.8W",
        "WiFi": "Intel Dual Band Wireless-AC 3165, 1×1 AC",
        "storage": "Storage:240GB SSD",
        "feature": "Features: HD Webcam, TF Card slot, Type-C"
    },
    {
        "name": "Toshiba Dynabook Satellite Pro C40-G-109 Celeron 5205U 14 HD Laptop",
        "categoryName": "all-laptop",
        "brand": "Toshiba",
        "price": "31,500৳",
        "img": "https://www.startech.com.bd/image/cache/catalog/la…c40-g-109/satellite-pro-c40-g-109-01-228x228.webp",
        "newPrice": "30,500৳ ",
        "processor": "Processor: Intel Celeron 5205U (2M Cache, 1.90 GHz)",
        "color": "Dark Blue",
        "Ram": "RAM: 4GB 3200MHz.",
        "CPU Cache": "2 MB",
        "Display Size": "Display: 14 HD (1,366 x 768)",
        "Battery Capacity": "45.6WHR",
        "WiFi": "802.11ac, agn (Dual Band) AC CM251",
        "storage": "Storage: 128GB SSD",
        "feature": "Features: Frameless black tile keyboard"
    },
    {
        "name": "Asus Vivobook X515MA Celeron N4020 15.6 FHD Laptop",
        "categoryName": "all-laptop",
        "brand": "ASUS",
        "price": "43,200৳",
        "img": "https://www.startech.com.bd/image/cache/catalog/la…obook-15-x515ea/vivobook-15-x515ea-01-228x228.jpg",
        "newPrice": "41,000৳",
        "processor": "Intel Celeron Processor N4020 (4M Cache, 1.10 GHz up to 2.80 GHz)",
        "color": "Black",
        "Ram": "4GB DDR4 RAM",
        "CPU Cache": "4MB",
        "Display Size": "15.6 Inch",
        "Battery Capacity": "38 Wh",
        "WiFi": "Wifi 802.11ac",
        "storage": "1TB HDD",
        "feature": "15.6 FHD (1920x1080) Display"
    },
    {
        "name": "Lenovo IdeaPad D330 10IGL Intel CDC N4020 10.1 HD Touch Laptop",
        "categoryName": "all-laptop",
        "brand": "Lenovo",
        "price": "36,999৳",
        "img": "https://www.startech.com.bd/image/cache/catalog/la…lton/passion-bx310u/passion-bx310u-01-228x228.jpg",
        "newPrice": "35,999৳",
        "processor": "Processor: Intel Celeron N4020 (4M Cache,1.10 GHz up to 2.80 GHz)",
        "color": "Mineral Gray",
        "Ram": "RAM: 4GB DDR4",
        "CPU Cache": "4MB",
        "Display Size": "10.1 Inch",
        "Battery Capacity": "39Wh",
        "WiFi": "802.11ac 1x1",
        "storage": "Storage: 128GB eMMC",
        "feature": "Antiscratch Brightness: 300nits, Aspect Ratio: 16:10, Color Gamut: 50% NTSC Display"
    },
    {
        "name": "Walton Passion BX310U Core i3 10th Gen 15.6 FHD Laptop",
        "categoryName": "all-laptop",
        "brand": "Walton",
        "price": "49,999৳",
        "img": "https://www.startech.com.bd/image/cache/catalog/laptop/doel/freedom-a9/a9-01-228x228.webp",
        "newPrice": "48,999৳",
        "processor": "Processor: Intel Core i3 10110U (4MB Cache, 2.1Ghz up to 4.1Ghz)",
        "color": "Black",
        "Ram": "RAM: 8GB 2666MHz",
        "CPU Cache": "4MB",
        "Display Size": "Display: 15.6 FHD (1920 x 1080)",
        "Battery Capacity": "36WH",
        "WiFi": "Intel Dual Band Wireless-AC 9462, 1x1 AC",
        "storage": "Storage: 512GB SSD",
        "feature": "Features: Built-in array microphone"
    },
    {
        "name": "HP 15s-eq1578AU AMD Athlon 3050U 15.6 FHD Laptop",
        "categoryName": "all-laptop",
        "brand": "HP",
        "price": "51,999৳",
        "img": "https://www.startech.com.bd/image/cache/catalog/la…-laptop/15s-eq1578au/15s-eq1578au-01-228x228.webp",
        "newPrice": "52,999৳",
        "processor": "Processor: AMD Athlon Silver 3050U (2.3 GHz up to 3.2GHz)",
        "color": "Silver",
        "Ram": "RAM: 8GB DDR4,",
        "CPU Cache": "4MB",
        "Display Size": "Display: 15.6 FHD (1920 x 1080)",
        "Battery Capacity": "41 Wh",
        "WiFi": "Realtek RTL8821CE-M 802.11a/b/g/n/ac (1x1) Wi-Fi",
        "storage": "Storage: 256GB SSD",
        "feature": "Features: Dual speakers, Type-C"
    },
    {
        "name": "Acer Aspire 3 A315-58 Core i3 11th Gen 512GB SSD 15.6 FHD Laptop",
        "categoryName": "all-laptop",
        "brand": "ACER",
        "price": "53,999৳",
        "img": "https://www.startech.com.bd/image/cache/catalog/la…ore-i5-1135g7-11th-gen-fhd-laptop-01-228x228.webp",
        "newPrice": "54,999৳",
        "processor": "Processor: Intel Core i3-1115G4 (6M Cache, 3.00 GHz up to 4.10 GHz)",
        "color": "Pure Silver",
        "Ram": "RAM: 8GB DDR4",
        "CPU Cache": "6MB",
        "Display Size": "Display: 15.6 FHD (1920 x 1080) LED",
        "Battery Capacity": "36.70Wh",
        "WiFi": "IEEE 802.11a/b/g/n/ac",
        "storage": "Storage: 512GB SSD",
        "feature": "Features: HD Camera, ComfyView Display"
    },
    {
        "name": "Apple MacBook Pro 13.3-Inch Retina Display M2 Chip 8GB RAM 512GB SSD Space Gray (MNEJ3)",
        "categoryName": "all-laptop",
        "brand": "MAC",
        "price": "185,000৳",
        "img": "https://www.startech.com.bd/image/cache/catalog/la…hip/macbook-pro-13-inch-m2-space-gray-228x228.jpg",
        "newPrice": "184,000৳",
        "processor": "Processor: Apple M2 chip, 8-core CPU with 4 performance & 4 efficiency cores",
        "color": "Space Gray",
        "Ram": "RAM: 8GB",
        "CPU Cache": "1MB",
        "Display Size": "Display: 13.3-inch (diagonal) LED-backlit display with IPS technology",
        "Battery Capacity": "58.2-watt-hour lithium-polymer battery",
        "WiFi": "802.11ax Wi-Fi 6 wireless networking IEEE 802.11a/b/g/n/ac compatible",
        "storage": "storage: 512GB SSD",
        "feature": "Features: Retina display, Magic Keyboard"
    },
    {
        "name": "MO06 MO09 Laptop Battery For HP Pavilion",
        "categoryName": "laptop-bettary",
        "battery-types": "Battery Type: Lithium-Ion",
        "voltage": "Voltage: 11.1V",
        "price": "1,600৳",
        "img": "https://www.startech.com.bd/image/cache/catalog/la…/Hp%20pavilion/m006-m009%20battery-01-228x228.jpg",
        "Battery Capacity": "Capacity: 62Wh 4400mAh",
        "cells": "Cells: 6 Cells",
        "warenty": "01-year"
    },
    {
        "name": "Laptop Battery For HP ProBook 4510s 4515s 4710s",
        "categoryName": "laptop-bettary",
        "battery-types": "Battery Type: Lithium-Ion",
        "voltage": "Voltage: 14.4V",
        "price": "1,500৳",
        "img": "https://www.startech.com.bd/image/cache/catalog/la…0mini%20/hp-4410s-notebook-battery-01-228x228.jpg",
        "Battery Capacity": "Capacity: 63.36Wh 4400mAh",
        "cells": "Cells: 6 Cells",
        "warenty": "01-year"
    },
    {
        "name": "Laptop Battery for HP MINI 210-1085TU",
        "categoryName": "laptop-bettary",
        "battery-types": "Battery Type: Lithium-Ion",
        "voltage": "Voltage: 10.8V",
        "price": "1,800৳",
        "img": "https://www.startech.com.bd/image/cache/catalog/la…y/hp%20mini%20/hp-mini-210-battery-01-228x228.jpg",
        "Battery Capacity": "Capacity: 5200mAh",
        "cells": "Cells: 6 Cells",
        "warenty": "01-year"
    },
    {
        "name": "RA04 Laptop Battery For HP ProBook 430 430 G1 430 G2 Series",
        "categoryName": "laptop-bettary",
        "battery-types": "Battery Type: Lithium-Ion",
        "voltage": "Voltage: 14.8V",
        "price": "1,600৳",
        "img": "https://www.startech.com.bd/image/cache/catalog/la…/Hp%20pavilion/m006-m009%20battery-01-228x228.jpg",
        "Battery Capacity": "Capacity: 2600mAh",
        "cells": "Cells: 4 Cells",
        "warenty": "01-year"
    },
    {
        "name": "RA04 Laptop Battery For HP ProBook 430 430 G1 430 G2 Series",
        "categoryName": "all-tv",
        "Resolution": "Resolution: 4K (3840×2160)",
        "Operating-system": "Operating System: Android 11",
        "price": "76,600৳",
        "RAM": "2GB",
        "ROM": "16GB",
        "Screen Size": "65``",
        "img": "https://www.startech.com.bd/image/cache/catalog/television/rowa/55u62/55u62-01-500x500.webp",
        "Build": "Chromecast Built-in",
        "warenty": "05 Years Parts & Panel Warranty"
    },
    {
        "name": "LG 32LK510B 32 HD LED Television",
        "categoryName": "all-tv",
        "Resolution": "Resolution: 1360x768 HD Resolution",
        "Operating-system": "Operating System: Android",
        "price": "76,600৳",
        "RAM": "1GB",
        "ROM": "8GB",
        "Screen Size": "32 inch",
        "img": "https://www.startech.com.bd/image/cache/catalog/te…0%9032sv22ks/sel%E2%80%9032sv22ks-01-500x500.webp",
        "Build": "Chromecast Built-in",
        "warenty": "5 Years Panel And 2 Years Parts Warranty"
    },
    {
        "name": "Vivo Y02 Smartphone (2/32GB)",
        "display": "Display: 6.51 HD+ Eye Protection Screen",
        "categoryName": "phone",
        "processor": "Processor: MediaTek MT6762 Helio P22 (12nm)",
        "cemera": "Camera: Single 8MP on Rear, 5MP Front",
        "feature": "Features: 5000mAh Battery",
        "price": "9,999৳",
        "img": "https://www.startech.com.bd/image/cache/catalog/mobile/vivo/y02/y02-blue-228x228.webp",
        "ram": "2GB",
        "warenty": "01-year Official warranty (To claim please visit the nearest Vivo Service Center)"
    },
    {
        "name": "OPPO A17 Smartphone (4/64GB)",
        "display": "Display: 6.56 HD+ Eye-care Display",
        "categoryName": "phone",
        "processor": "Processor: Mediatek MT6765 Helio G35 (12 nm)",
        "cemera": "Camera: Dual 50+2MP on Rear, 5MP Front",
        "feature": "Features: Side-mounted Fingerprint, IPX4",
        "price": "9,999৳",
        "img": "https://www.startech.com.bd/image/cache/catalog/mobile/oppo/a17/a17-blue-228x228.webp",
        "ram": "2GB",
        "warenty": "01-year Official warranty (To claim please visit the nearest OPPO Service Center)"
    },
    {
        "name": "WiWU 10-inch LCD Writing Drawing Board Tablet for Kids",
        "display-size": "Size: 10-inch",
        "categoryName": "tablet",
        "metrials": "Material: ABS+Polymer Solid-state Liquid Crystal",
        "feature": "One-click clear Convenient & Fast",
        "price": "1,999৳",
        "img": "https://www.startech.com.bd/image/cache/catalog/gr…ng-tablet/wiwu-lcd-drawing-tablet-02-500x500.webp",
        "warenty": "01-year Official warranty (To claim please visit the nearest OPPO Service Center)"
    },
    {
        "name": "Samsung Galaxy Tab A 8.0 Snapdragon 429 2GB RAM 32GB ROM Android Tablet",
        "display-size": "Display: 8-inch WXGA Display",
        "categoryName": "tablet",
        "metrials": "CPU: Snapdragon 429, GPU: Adreno 504",
        "feature": "Battery: 5100 mAh",
        "price": "1,999৳",
        "img": "https://www.startech.com.bd/image/cache/catalog/ta…tab-a-8-0/samsung-galaxy-tab-a-8-0-01-228x228.jpg",
        "warenty": "01-year Official warranty (To claim please visit the nearest OPPO Service Center)"
    },
    {
        "name": "SJCAM SJ8 Pro 12MP 4K Wi-Fi Dual Screen Waterproof Action Camera",
        "display-size": "Front Screen: 0.96 OLED, Main Screen: 2.33 IPS Touch Screen",
        "categoryName": "action-cemera",
        "resulation": "4k/60fps Video Resolution",
        "feature": "1200 Mah Battery, Dual Microphones",
        "price": "17,500৳",
        "img": "https://www.startech.com.bd/image/cache/catalog/ca…tion-camera/sjcam/sj8-pro/sj8-pro-01-228x228.jpeg",
        "warenty": "01-year Official warranty (To claim please visit the nearest OPPO Service Center)"
    },
    {
        "name": "AKASO Brave 7 20MP 4K Waterproof Touch Screen Wifi Remote Control Action Camera",
        "display-size": "Dual color screens: 1.2 front screen + 2 touch screen",
        "categoryName": "action-cemera",
        "resulation": "4K 30FPS video and 20MP photo",
        "feature": "IPX8 waterproof, voice control & Smart remote control",
        "price": "18,000৳",
        "img": "https://www.startech.com.bd/image/cache/catalog/ca…ction-camera/akaso/brave-7/brave-7-01-228x228.jpg",
        "warenty": "01-year Official warranty (To claim please visit the nearest OPPO Service Center)"
    },
    {
        "name": "XINJI COBEE C1 Waterproof Smart Watch",
        "display-size": "1.69 HD (240x280) Display",
        "categoryName": "smart-watch",
        "resulation": "4K 30FPS video and 20MP photo",
        "feature": "260 mAh Battery, Magnetic Charging,5ATM Waterproof",
        "price": "2,550৳",
        "img": "https://www.startech.com.bd/image/cache/catalog/sm…-watch/xiaomi/imlab-kw66/imlab-kw66-1-228x228.jpg",
        "warenty": "01-year Official warranty (To claim please visit the nearest XINJI Service Center)"
    },
    {
        "name": "Xiaomi Haylou Solar LS05-1 Smart Watch Black",
        "display-size": "1.28 Inch Round TFT Screen",
        "categoryName": "smart-watch",
        "resulation": "4K 30FPS video and 20MP photo",
        "feature": "IP68 Waterproof, Metal Body,Multiple Sports Modes",
        "price": "2,700৳",
        "img": "https://www.startech.com.bd/image/cache/catalog/wa…-solar-ls05-1/haylou-solar-ls05-1-001-228x228.jpg",
        "warenty": "01-year Official warranty (To claim please visit the nearest Xiaomi Service Center)"
    },
    {
        "name": "Tenda AC8 AC1200 Dual-Band 4 Antenna Gigabit Smart Wi-Fi Router",
        "categoryName": "router",
        "support": "Support Wi-Fi Schedule",
        "feature": "Dual-Band: 2.4 & 5GHz,4* 6dBi External Antennas",
        "price": "3,050৳",
        "img": "https://www.startech.com.bd/image/cache/catalog/router/tenda/ac8-ac1200/ac8-ac1200-228x228.png"
    },
    {
        "name": "Tenda AC23 2033mbps AC2100 7 Antenna Dual Band Gigabit Wireless Router (Black)",
        "categoryName": "router",
        "support": "Support Beamforming+",
        "feature": "Support Guest Network,Unify 2.4GHz and 5GHz signals",
        "price": "4,275৳",
        "img": "https://www.startech.com.bd/image/cache/catalog/router/tenda/ac8-ac1200/ac8-ac1200-228x228.png"
    },
    {
        "name": "HAVIT HV-H2105D Headphone with Mic",
        "categoryName": "headphone",
        "frequency": "Frequency: 20-20,000Hz",
        "Sensitivity": "Sensitivity: 102±3dB/mW",
        "cable-length": "Cable Length: 1.2M±0.15M",
        "price": "4,75৳",
        "img": "https://www.startech.com.bd/image/cache/catalog/headphone/havit/h2105d/h2105d-228x228.jpg"
    },
    {
        "name": "A4Tech HS-9 Stereo Headphone Black",
        "categoryName": "headphone",
        "frequency": "Frequency: 20 Hz - 20 KHz",
        "Sensitivity": "Sensitivity: 100 Db",
        "cable-length": "Cable Length: 180 cm",
        "price": "700৳",
        "img": "https://www.startech.com.bd/image/cache/catalog/he…-9/a4tech-hs-9-stereo-headphone-black-228x228.jpg"
    },
    {
        "name": "UiiSii C1 Type-C Heavy Bass Earphone",
        "categoryName": "ear-phone",
        "frequency": "Frequency: 20-20000HZ",
        "interface": "Interface: Type C",
        "cable-length": "Cable length: 1.2m",
        "price": "350৳",
        "img": "https://www.startech.com.bd/image/cache/catalog/earphone/uiisii/c1-type-c/c1-type-c-01-228x228.webp"
    },
    {
        "name": "Realme Buds Classic RMA2001 Earphones Black",
        "categoryName": "ear-phone",
        "frequency": "Frequency: 20-20000HZ-",
        "interface": "Richer Bass",
        "cable-length": "Cable length: 1.2m",
        "price": "650৳",
        "img": "https://www.startech.com.bd/image/cache/catalog/ea…-classic-rma2001/buds-classic-rma2001-228x228.jpg"
    },
    {
        "name": "JOYROOM JR-ML01 Bluetooth Wireless Speaker",
        "categoryName": "blue-speakers",
        "version": "Bluetooth version: V5.0",
        "battery": "Battery: 2200mAh Built-in lithium",
        "charge-time": "2-3 hour",
        "price": "1,650৳",
        "img": "https://www.startech.com.bd/image/cache/catalog/speaker/joyroom/jr-ml01/jr-ml01-01-228x228.jpg"
    },
    {
        "name": "Yison Celebrat SP-3 Portable Bluetooth Speaker",
        "categoryName": "blue-speakers",
        "version": "Bluetooth version: V5.0",
        "battery": "Battery Capacity: 600mAh",
        "charge-time": "2-3 hour",
        "price": "1,550৳",
        "img": "https://www.startech.com.bd/image/cache/catalog/sp…-sp-3-portable-blutooth-speaker-black-228x228.jpg"
    },
    {
        "name": "PS4 DualShock 4 Wireless Controller Black (Original)",
        "categoryName": "game-console",
        "touch": "SHARE button, Touch pad",
        "Motion": "Motion sensors, Stereo headset jack",
        "price": "6,700৳",
        "img": "https://www.startech.com.bd/image/cache/catalog/ga…/sony/ps4-dualshock-4/ps4-dualshock-4-228x228.jpg"
    },
    {
        "name": "PlayStation 5 DualSense Wireless Controller",
        "categoryName": "game-console",
        "touch": "Built-in microphone and headset jack",
        "Motion": "Motion sensor, Create button",
        "price": "8,100৳",
        "img": "https://www.startech.com.bd/image/cache/catalog/game-pad/sony/dualsense/dualsense-228x228.jpg"
    }
]